odoo/addons/l10n_br_fiscal/README.rst
odoo/addons/l10n_br_fiscal/__init__.py
odoo/addons/l10n_br_fiscal/__manifest__.py
odoo/addons/l10n_br_fiscal/hooks.py
odoo/addons/l10n_br_fiscal/constants/fiscal.py
odoo/addons/l10n_br_fiscal/constants/icms.py
odoo/addons/l10n_br_fiscal/constants/ipi.py
odoo/addons/l10n_br_fiscal/constants/issqn.py
odoo/addons/l10n_br_fiscal/constants/mdfe.py
odoo/addons/l10n_br_fiscal/constants/pis_cofins.py
odoo/addons/l10n_br_fiscal/data/ir_cron.xml
odoo/addons/l10n_br_fiscal/data/l10n_br_fiscal.cest.csv
odoo/addons/l10n_br_fiscal/data/l10n_br_fiscal.cfop.csv
odoo/addons/l10n_br_fiscal/data/l10n_br_fiscal.cnae.csv
odoo/addons/l10n_br_fiscal/data/l10n_br_fiscal.cst.csv
odoo/addons/l10n_br_fiscal/data/l10n_br_fiscal.document.type.csv
odoo/addons/l10n_br_fiscal/data/l10n_br_fiscal.icms.relief.csv
odoo/addons/l10n_br_fiscal/data/l10n_br_fiscal.nbm.csv
odoo/addons/l10n_br_fiscal/data/l10n_br_fiscal.nbs.csv
odoo/addons/l10n_br_fiscal/data/l10n_br_fiscal.ncm.csv
odoo/addons/l10n_br_fiscal/data/l10n_br_fiscal.product.genre.csv
odoo/addons/l10n_br_fiscal/data/l10n_br_fiscal.service.type.csv
odoo/addons/l10n_br_fiscal/data/l10n_br_fiscal.tax.csv
odoo/addons/l10n_br_fiscal/data/l10n_br_fiscal.tax.group.csv
odoo/addons/l10n_br_fiscal/data/l10n_br_fiscal.tax.ipi.control.seal.csv
odoo/addons/l10n_br_fiscal/data/l10n_br_fiscal.tax.ipi.guideline.class.csv
odoo/addons/l10n_br_fiscal/data/l10n_br_fiscal.tax.ipi.guideline.csv
odoo/addons/l10n_br_fiscal/data/l10n_br_fiscal.tax.pis.cofins.base.csv
odoo/addons/l10n_br_fiscal/data/l10n_br_fiscal.tax.pis.cofins.credit.csv
odoo/addons/l10n_br_fiscal/data/l10n_br_fiscal.tax.pis.cofins.csv
odoo/addons/l10n_br_fiscal/data/l10n_br_fiscal_cfop_data.xml
odoo/addons/l10n_br_fiscal/data/l10n_br_fiscal_comment_data.xml
odoo/addons/l10n_br_fiscal/data/l10n_br_fiscal_data.xml
odoo/addons/l10n_br_fiscal/data/l10n_br_fiscal_email_template.xml
odoo/addons/l10n_br_fiscal/data/l10n_br_fiscal_icms_tax_definition_data.xml
odoo13_addon_l10n_br_fiscal-13.0.3.1.0.dist-info/METADATA
odoo13_addon_l10n_br_fiscal-13.0.3.1.0.dist-info/WHEEL
odoo13_addon_l10n_br_fiscal-13.0.3.1.0.dist-info/top_level.txt
odoo13_addon_l10n_br_fiscal-13.0.3.1.0.dist-info/RECORD
